{
    "textures": {
        "clock": "items/misc/clock/clock",
        "h0": "items/misc/clock/h0",
        "h1": "items/misc/clock/h1",
        "h2": "items/misc/clock/h2",
        "h3": "items/misc/clock/h3",
        "h4": "items/misc/clock/h4",
        "h5": "items/misc/clock/h5",
        "h6": "items/misc/clock/h6",
        "h7": "items/misc/clock/h7",
        "h8": "items/misc/clock/h8",
        "h9": "items/misc/clock/h9",
        "h10": "items/misc/clock/h10",
        "h11": "items/misc/clock/h11",
        "h12": "items/misc/clock/h12",
        "h13": "items/misc/clock/h13",
        "h14": "items/misc/clock/h14",
        "h15": "items/misc/clock/h15",
        "m0": "items/misc/clock/m0",
        "m1": "items/misc/clock/m1",
        "m2": "items/misc/clock/m2",
        "m3": "items/misc/clock/m3",
        "m4": "items/misc/clock/m4",
        "m5": "items/misc/clock/m5",
        "m6": "items/misc/clock/m6",
        "m7": "items/misc/clock/m7",
        "m8": "items/misc/clock/m8",
        "m9": "items/misc/clock/m9",
        "m10": "items/misc/clock/m10",
        "m11": "items/misc/clock/m11",
        "m12": "items/misc/clock/m12",
        "m13": "items/misc/clock/m13",
        "m14": "items/misc/clock/m14",
        "m15": "items/misc/clock/m15"
    },
    "elements": [
        {
            "comment": "face",
            "from": [ -0.8000000000000007, -0.8000000000000007, 8.0 ],
            "to": [ 16.8, 16.8, 8.0 ],
            "faces": {
                "north": { "uv": [ 0, 5, 7, 12 ], "texture": "#clock" }
            }
        },
        {
            "comment": "face",
            "from": [ -0.8000000000000007, -0.8000000000000007, 8.022 ],
            "to": [ 16.8, 16.8, 8.022 ],
            "rotation": { "origin": [ 8.0, 8.0, -9.600000000000001 ], "axis": "z", "angle": 45 },
            "faces": {
                "north": { "uv": [ 0, 5, 7, 12 ], "texture": "#clock" }
            }
        },
        {
            "comment": "inside",
            "from": [ 5.8, 5.8, 8.110000000000001 ],
            "to": [ 10.2, 10.2, 8.110000000000001 ],
            "faces": {
                "north": { "uv": [ 8, 8, 16, 16 ], "texture": "#clock" }
            }
        },
        {
            "comment": "back",
            "from": [ -0.8000000000000007, -0.8000000000000007, 10.2 ],
            "to": [ 16.8, 16.8, 10.2 ],
            "faces": {
                "south": { "uv": [ 8, 0, 16, 8 ], "texture": "#clock" }
            }
        },
        {
            "comment": "back",
            "from": [ -0.8000000000000007, -0.8000000000000007, 10.178 ],
            "to": [ 16.8, 16.8, 10.178 ],
            "rotation": { "origin": [ 8.0, 8.0, -9.600000000000001 ], "axis": "z", "angle": 45 },
            "faces": {
                "south": { "uv": [ 8, 0, 16, 8 ], "texture": "#clock" }
            }
        },
        {
            "comment": "edge",
            "from": [ 3.5999999999999996, 16.8, 6.459999999999999 ],
            "to": [ 12.4, 19.0, 10.639999999999999 ],
            "faces": {
                "north": { "uv": [ 4, 0, 8, 1 ], "texture": "#clock" },
                "south": { "uv": [ 4, 0, 8, 1 ], "texture": "#clock" },
                "up":    { "uv": [ 4, 0, 8, 1 ], "texture": "#clock" },
                "down":  { "uv": [ 4, 0, 8, 1 ], "texture": "#clock" }
            }
        },
        {
            "comment": "edge",
            "from": [ -3.0, 3.5999999999999996, 6.459999999999999 ],
            "to": [ -0.8000000000000007, 12.4, 10.639999999999999 ],
            "faces": {
                "north": { "uv": [ 4, 1, 8, 2 ], "texture": "#clock", "rotation": 90 },
                "south": { "uv": [ 4, 1, 8, 2 ], "texture": "#clock", "rotation": 90 },
                "east":  { "uv": [ 4, 1, 8, 2 ], "texture": "#clock", "rotation": 90 },
                "west":  { "uv": [ 4, 1, 8, 2 ], "texture": "#clock", "rotation": 90 }
            }
        },
        {
            "comment": "edge",
            "from": [ 3.5999999999999996, -3.0, 6.459999999999999 ],
            "to": [ 12.4, -0.8000000000000007, 10.639999999999999 ],
            "faces": {
                "north": { "uv": [ 4, 2, 8, 3 ], "texture": "#clock", "rotation": 180 },
                "south": { "uv": [ 4, 2, 8, 3 ], "texture": "#clock", "rotation": 180 },
                "up":    { "uv": [ 4, 2, 8, 3 ], "texture": "#clock", "rotation": 180 },
                "down":  { "uv": [ 4, 2, 8, 3 ], "texture": "#clock", "rotation": 180 }
            }
        },
        {
            "comment": "edge",
            "from": [ 16.8, 3.5999999999999996, 6.459999999999999 ],
            "to": [ 19.0, 12.4, 10.639999999999999 ],
            "faces": {
                "north": { "uv": [ 4, 3, 8, 4 ], "texture": "#clock", "rotation": 270 },
                "south": { "uv": [ 4, 3, 8, 4 ], "texture": "#clock", "rotation": 270 },
                "east":  { "uv": [ 4, 3, 8, 4 ], "texture": "#clock", "rotation": 270 },
                "west":  { "uv": [ 4, 3, 8, 4 ], "texture": "#clock", "rotation": 270 }
            }
        },
        {
            "comment": "edge",
            "from": [ -5.733809511662429, 16.8, 6.481999999999999 ],
            "to": [ 3.5999999999999996, 19.0, 10.617999999999999 ],
            "rotation": { "origin": [ 3.5999999999999996, 19.0, -9.600000000000001 ], "axis": "z", "angle": 45 },
            "faces": {
                "north": { "uv": [ 0, 1, 4, 2 ], "texture": "#clock" },
                "south": { "uv": [ 0, 1, 4, 2 ], "texture": "#clock" },
                "up":    { "uv": [ 0, 1, 4, 2 ], "texture": "#clock" },
                "down":  { "uv": [ 0, 1, 4, 2 ], "texture": "#clock" }
            }
        },
        {
            "comment": "edge",
            "from": [ -3.0, -5.733809511662429, 6.481999999999999 ],
            "to": [ -0.8000000000000007, 3.5999999999999996, 10.617999999999999 ],
            "rotation": { "origin": [ -3.0, 3.5999999999999996, -9.600000000000001 ], "axis": "z", "angle": 45 },
            "faces": {
                "north": { "uv": [ 0, 2, 4, 3 ], "texture": "#clock", "rotation": 90 },
                "south": { "uv": [ 0, 2, 4, 3 ], "texture": "#clock", "rotation": 90 },
                "east":  { "uv": [ 0, 2, 4, 3 ], "texture": "#clock", "rotation": 90 },
                "west":  { "uv": [ 0, 2, 4, 3 ], "texture": "#clock", "rotation": 90 }
            }
        },
        {
            "comment": "edge",
            "from": [ 12.4, -3.0, 6.481999999999999 ],
            "to": [ 21.73380951166243, -0.8000000000000007, 10.617999999999999 ],
            "rotation": { "origin": [ 12.4, -3.0, -9.600000000000001 ], "axis": "z", "angle": 45 },
            "faces": {
                "north": { "uv": [ 0, 3, 4, 4 ], "texture": "#clock", "rotation": 180 },
                "south": { "uv": [ 0, 3, 4, 4 ], "texture": "#clock", "rotation": 180 },
                "up":    { "uv": [ 0, 3, 4, 4 ], "texture": "#clock", "rotation": 180 },
                "down":  { "uv": [ 0, 3, 4, 4 ], "texture": "#clock", "rotation": 180 }
            }
        },
        {
            "comment": "edge",
            "from": [ 16.8, 12.4, 6.481999999999999 ],
            "to": [ 19.0, 21.73380951166243, 10.617999999999999 ],
            "rotation": { "origin": [ 19.0, 12.4, -9.600000000000001 ], "axis": "z", "angle": 45 },
            "faces": {
                "north": { "uv": [ 0, 0, 4, 1 ], "texture": "#clock", "rotation": 270 },
                "south": { "uv": [ 0, 0, 4, 1 ], "texture": "#clock", "rotation": 270 },
                "east":  { "uv": [ 0, 0, 4, 1 ], "texture": "#clock", "rotation": 270 },
                "west":  { "uv": [ 0, 0, 4, 1 ], "texture": "#clock", "rotation": 270 }
            }
        },
        {
            "comment": "back panel",
            "from": [ 1.3999999999999995, 1.3999999999999995, 9.1 ],
            "to": [ 14.600000000000001, 14.600000000000001, 10.530000000000001 ],
            "rotation": { "origin": [ 8.0, 8.0, -9.600000000000001 ], "axis": "z", "angle": 45 },
            "faces": {
                "south": { "uv": [ 0, 12.01, 4, 16 ], "texture": "#clock" },
                "up":    { "uv": [ 0, 12, 4, 13 ], "texture": "#clock" },
                "down":  { "uv": [ 0, 15, 4, 16 ], "texture": "#clock" },
                "east":  { "uv": [ 0, 12, 1, 16 ], "texture": "#clock" },
                "west":  { "uv": [ 3, 12, 4, 16 ], "texture": "#clock" }
            }
        },
        {
            "comment": "gears",
            "from": [ 3.380000000000001, 3.380000000000001, 9.1 ],
            "to": [ 12.62, 12.62, 10.508000000000001 ],
            "faces": {
                "south": { "uv": [ 8, 8, 16, 16 ], "texture": "#clock" }
            }
        },
        {
            "comment": "number",
            "from": [ 7.45, 14.05, 7.45 ],
            "to": [ 8.55, 16.25, 8.0 ],
            "faces": {
                "north": { "uv": [ 0, 4, 1, 5 ], "texture": "#clock" },
                "east":  { "uv": [ 0, 4, 1, 5 ], "texture": "#clock" },
                "west":  { "uv": [ 0, 4, 1, 5 ], "texture": "#clock" },
                "up":    { "uv": [ 0, 4, 1, 5 ], "texture": "#clock" },
                "down":  { "uv": [ 0, 4, 1, 5 ], "texture": "#clock" }
            }
        },
        {
            "comment": "number",
            "from": [ 7.45, 0.29999999999999893, 7.45 ],
            "to": [ 8.55, 1.3999999999999995, 8.0 ],
            "faces": {
                "north": { "uv": [ 0, 4, 1, 5 ], "texture": "#clock" },
                "east":  { "uv": [ 0, 4, 1, 5 ], "texture": "#clock" },
                "west":  { "uv": [ 0, 4, 1, 5 ], "texture": "#clock" },
                "up":    { "uv": [ 0, 4, 1, 5 ], "texture": "#clock" },
                "down":  { "uv": [ 0, 4, 1, 5 ], "texture": "#clock" }
            }
        },
        {
            "comment": "number",
            "from": [ 14.600000000000001, 7.45, 7.45 ],
            "to": [ 15.700000000000001, 8.55, 8.0 ],
            "faces": {
                "north": { "uv": [ 0, 4, 1, 5 ], "texture": "#clock" },
                "east":  { "uv": [ 0, 4, 1, 5 ], "texture": "#clock" },
                "west":  { "uv": [ 0, 4, 1, 5 ], "texture": "#clock" },
                "up":    { "uv": [ 0, 4, 1, 5 ], "texture": "#clock" },
                "down":  { "uv": [ 0, 4, 1, 5 ], "texture": "#clock" }
            }
        },
        {
            "comment": "number",
            "from": [ 0.29999999999999893, 7.45, 7.45 ],
            "to": [ 1.3999999999999995, 8.55, 8.0 ],
            "faces": {
                "north": { "uv": [ 0, 4, 1, 5 ], "texture": "#clock" },
                "east":  { "uv": [ 0, 4, 1, 5 ], "texture": "#clock" },
                "west":  { "uv": [ 0, 4, 1, 5 ], "texture": "#clock" },
                "up":    { "uv": [ 0, 4, 1, 5 ], "texture": "#clock" },
                "down":  { "uv": [ 0, 4, 1, 5 ], "texture": "#clock" }
            }
        },
        {
            "comment": "number",
            "from": [ 4.04, 13.5, 7.45 ],
            "to": [ 5.140000000000001, 14.600000000000001, 8.0 ],
            "faces": {
                "north": { "uv": [ 0, 4, 1, 5 ], "texture": "#clock" },
                "east":  { "uv": [ 0, 4, 1, 5 ], "texture": "#clock" },
                "west":  { "uv": [ 0, 4, 1, 5 ], "texture": "#clock" },
                "up":    { "uv": [ 0, 4, 1, 5 ], "texture": "#clock" },
                "down":  { "uv": [ 0, 4, 1, 5 ], "texture": "#clock" }
            }
        },
        {
            "comment": "number",
            "from": [ 10.860000000000001, 13.5, 7.45 ],
            "to": [ 11.96, 14.600000000000001, 8.0 ],
            "faces": {
                "north": { "uv": [ 0, 4, 1, 5 ], "texture": "#clock" },
                "east":  { "uv": [ 0, 4, 1, 5 ], "texture": "#clock" },
                "west":  { "uv": [ 0, 4, 1, 5 ], "texture": "#clock" },
                "up":    { "uv": [ 0, 4, 1, 5 ], "texture": "#clock" },
                "down":  { "uv": [ 0, 4, 1, 5 ], "texture": "#clock" }
            }
        },
        {
            "comment": "number",
            "from": [ 4.04, 1.3999999999999995, 7.45 ],
            "to": [ 5.140000000000001, 2.5, 8.0 ],
            "faces": {
                "north": { "uv": [ 0, 4, 1, 5 ], "texture": "#clock" },
                "east":  { "uv": [ 0, 4, 1, 5 ], "texture": "#clock" },
                "west":  { "uv": [ 0, 4, 1, 5 ], "texture": "#clock" },
                "up":    { "uv": [ 0, 4, 1, 5 ], "texture": "#clock" },
                "down":  { "uv": [ 0, 4, 1, 5 ], "texture": "#clock" }
            }
        },
        {
            "comment": "number",
            "from": [ 10.860000000000001, 1.3999999999999995, 7.45 ],
            "to": [ 11.96, 2.5, 8.0 ],
            "faces": {
                "north": { "uv": [ 0, 4, 1, 5 ], "texture": "#clock" },
                "east":  { "uv": [ 0, 4, 1, 5 ], "texture": "#clock" },
                "west":  { "uv": [ 0, 4, 1, 5 ], "texture": "#clock" },
                "up":    { "uv": [ 0, 4, 1, 5 ], "texture": "#clock" },
                "down":  { "uv": [ 0, 4, 1, 5 ], "texture": "#clock" }
            }
        },
        {
            "comment": "number",
            "from": [ 13.5, 4.04, 7.45 ],
            "to": [ 14.600000000000001, 5.140000000000001, 8.0 ],
            "faces": {
                "north": { "uv": [ 0, 4, 1, 5 ], "texture": "#clock" },
                "east":  { "uv": [ 0, 4, 1, 5 ], "texture": "#clock" },
                "west":  { "uv": [ 0, 4, 1, 5 ], "texture": "#clock" },
                "up":    { "uv": [ 0, 4, 1, 5 ], "texture": "#clock" },
                "down":  { "uv": [ 0, 4, 1, 5 ], "texture": "#clock" }
            }
        },
        {
            "comment": "number",
            "from": [ 13.5, 10.860000000000001, 7.45 ],
            "to": [ 14.600000000000001, 11.96, 8.0 ],
            "faces": {
                "north": { "uv": [ 0, 4, 1, 5 ], "texture": "#clock" },
                "east":  { "uv": [ 0, 4, 1, 5 ], "texture": "#clock" },
                "west":  { "uv": [ 0, 4, 1, 5 ], "texture": "#clock" },
                "up":    { "uv": [ 0, 4, 1, 5 ], "texture": "#clock" },
                "down":  { "uv": [ 0, 4, 1, 5 ], "texture": "#clock" }
            }
        },
        {
            "comment": "number",
            "from": [ 1.3999999999999995, 4.04, 7.45 ],
            "to": [ 2.5, 5.140000000000001, 8.0 ],
            "faces": {
                "north": { "uv": [ 0, 4, 1, 5 ], "texture": "#clock" },
                "east":  { "uv": [ 0, 4, 1, 5 ], "texture": "#clock" },
                "west":  { "uv": [ 0, 4, 1, 5 ], "texture": "#clock" },
                "up":    { "uv": [ 0, 4, 1, 5 ], "texture": "#clock" },
                "down":  { "uv": [ 0, 4, 1, 5 ], "texture": "#clock" }
            }
        },
        {
            "comment": "number",
            "from": [ 1.3999999999999995, 10.860000000000001, 7.45 ],
            "to": [ 2.5, 11.96, 8.0 ],
            "faces": {
                "north": { "uv": [ 0, 4, 1, 5 ], "texture": "#clock" },
                "east":  { "uv": [ 0, 4, 1, 5 ], "texture": "#clock" },
                "west":  { "uv": [ 0, 4, 1, 5 ], "texture": "#clock" },
                "up":    { "uv": [ 0, 4, 1, 5 ], "texture": "#clock" },
                "down":  { "uv": [ 0, 4, 1, 5 ], "texture": "#clock" }
            }
        },
        {
            "comment": "top",
            "from": [ 6.9, 19.0, 6.9 ],
            "to": [ 9.1, 21.200000000000003, 9.1 ],
            "faces": {
                "north": { "uv": [ 0, 0, 1, 1 ], "texture": "#clock" },
                "east":  { "uv": [ 0, 0, 1, 1 ], "texture": "#clock" },
                "west":  { "uv": [ 0, 0, 1, 1 ], "texture": "#clock" },
                "up":    { "uv": [ 0, 0, 1, 1 ], "texture": "#clock" },
                "south": { "uv": [ 0, 0, 1, 1 ], "texture": "#clock" }
            }
        },
        {
            "comment": "hands stick",
            "from": [ 7.45, 7.45, 7.45 ],
            "to": [ 8.55, 8.55, 9.1 ],
            "faces": {
                "north": { "uv": [ 0, 4, 1, 5 ], "texture": "#clock" },
                "east":  { "uv": [ 0, 4, 1, 5 ], "texture": "#clock" },
                "west":  { "uv": [ 0, 4, 1, 5 ], "texture": "#clock" },
                "up":    { "uv": [ 0, 4, 1, 5 ], "texture": "#clock" },
                "down":  { "uv": [ 0, 4, 1, 5 ], "texture": "#clock" }
            }
        },
        {
            "comment": "minute hand",
            "from": [ 7.45, 6.9, 6.35 ],
            "to": [ 8.55, 15.700000000000001, 7.45 ],
            "rotation": { "origin": [ 8.0, 8.0, 8.0 ], "axis": "z", "angle": -22.5 },
            "faces": {
                "north": { "uv": [ 0, 0, 1, 16 ], "texture": "#m15" },
                "south": { "uv": [ 0, 0, 1, 16 ], "texture": "#m15" },
                "east":  { "uv": [ 0, 0, 1, 16 ], "texture": "#m15" },
                "west":  { "uv": [ 0, 0, 1, 16 ], "texture": "#m15" },
                "down":  { "uv": [ 0, 12, 1, 16 ], "texture": "#m15" },
                "up":    { "uv": [ 0, 0, 1, 4 ], "texture": "#m15" }
            }
        },
        {
            "comment": "minute hand",
            "from": [ 7.45, 6.9, 6.35 ],
            "to": [ 8.55, 15.700000000000001, 7.45 ],
            "faces": {
                "north": { "uv": [ 0, 0, 1, 16 ], "texture": "#m0" },
                "south": { "uv": [ 0, 0, 1, 16 ], "texture": "#m0" },
                "east":  { "uv": [ 0, 0, 1, 16 ], "texture": "#m0" },
                "west":  { "uv": [ 0, 0, 1, 16 ], "texture": "#m0" },
                "down":  { "uv": [ 0, 12, 1, 16 ], "texture": "#m0" },
                "up":    { "uv": [ 0, 0, 1, 4 ], "texture": "#m0" }
            }
        },
        {
            "comment": "minute hand",
            "from": [ 7.45, 6.9, 6.35 ],
            "to": [ 8.55, 15.700000000000001, 7.45 ],
            "rotation": { "origin": [ 8.0, 8.0, 8.0 ], "axis": "z", "angle": 22.5 },
            "faces": {
                "north": { "uv": [ 0, 0, 1, 16 ], "texture": "#m1" },
                "south": { "uv": [ 0, 0, 1, 16 ], "texture": "#m1" },
                "east":  { "uv": [ 0, 0, 1, 16 ], "texture": "#m1" },
                "west":  { "uv": [ 0, 0, 1, 16 ], "texture": "#m1" },
                "down":  { "uv": [ 0, 12, 1, 16 ], "texture": "#m1" },
                "up":    { "uv": [ 0, 0, 1, 4 ], "texture": "#m1" }
            }
        },
        {
            "comment": "minute hand",
            "from": [ 7.45, 6.9, 6.35 ],
            "to": [ 8.55, 15.700000000000001, 7.45 ],
            "rotation": { "origin": [ 8.0, 8.0, 8.0 ], "axis": "z", "angle": 45 },
            "faces": {
                "north": { "uv": [ 0, 0, 1, 16 ], "texture": "#m2" },
                "south": { "uv": [ 0, 0, 1, 16 ], "texture": "#m2" },
                "east":  { "uv": [ 0, 0, 1, 16 ], "texture": "#m2" },
                "west":  { "uv": [ 0, 0, 1, 16 ], "texture": "#m2" },
                "down":  { "uv": [ 0, 12, 1, 16 ], "texture": "#m2" },
                "up":    { "uv": [ 0, 0, 1, 4 ], "texture": "#m2" }
            }
        },
        {
            "comment": "minute hand",
            "from": [ 0.29999999999999893, 7.45, 6.35 ],
            "to": [ 9.1, 8.55, 7.45 ],
            "rotation": { "origin": [ 8.0, 8.0, 8.0 ], "axis": "z", "angle": -22.5 },
            "faces": {
                "north": { "uv": [ 0, 0, 1, 16 ], "texture": "#m3", "rotation": 90 },
                "south": { "uv": [ 0, 0, 1, 16 ], "texture": "#m3", "rotation": 90 },
                "east":  { "uv": [ 0, 0, 1, 16 ], "texture": "#m3", "rotation": 90 },
                "west":  { "uv": [ 0, 0, 1, 16 ], "texture": "#m3", "rotation": 90 },
                "down":  { "uv": [ 0, 12, 1, 16 ], "texture": "#m3", "rotation": 90 },
                "up":    { "uv": [ 0, 0, 1, 4 ], "texture": "#m3", "rotation": 90 }
            }
        },
        {
            "comment": "minute hand",
            "from": [ 0.29999999999999893, 7.45, 6.35 ],
            "to": [ 9.1, 8.55, 7.45 ],
            "faces": {
                "north": { "uv": [ 0, 0, 1, 16 ], "texture": "#m4", "rotation": 90 },
                "south": { "uv": [ 0, 0, 1, 16 ], "texture": "#m4", "rotation": 90 },
                "east":  { "uv": [ 0, 0, 1, 16 ], "texture": "#m4", "rotation": 90 },
                "west":  { "uv": [ 0, 0, 1, 16 ], "texture": "#m4", "rotation": 90 },
                "down":  { "uv": [ 0, 12, 1, 16 ], "texture": "#m4", "rotation": 90 },
                "up":    { "uv": [ 0, 0, 1, 4 ], "texture": "#m4", "rotation": 90 }
            }
        },
        {
            "comment": "minute hand",
            "from": [ 0.29999999999999893, 7.45, 6.35 ],
            "to": [ 9.1, 8.55, 7.45 ],
            "rotation": { "origin": [ 8.0, 8.0, 8.0 ], "axis": "z", "angle": 22.5 },
            "faces": {
                "north": { "uv": [ 0, 0, 1, 16 ], "texture": "#m5", "rotation": 90 },
                "south": { "uv": [ 0, 0, 1, 16 ], "texture": "#m5", "rotation": 90 },
                "east":  { "uv": [ 0, 0, 1, 16 ], "texture": "#m5", "rotation": 90 },
                "west":  { "uv": [ 0, 0, 1, 16 ], "texture": "#m5", "rotation": 90 },
                "down":  { "uv": [ 0, 12, 1, 16 ], "texture": "#m5", "rotation": 90 },
                "up":    { "uv": [ 0, 0, 1, 4 ], "texture": "#m5", "rotation": 90 }
            }
        },
        {
            "comment": "minute hand",
            "from": [ 0.29999999999999893, 7.45, 6.35 ],
            "to": [ 9.1, 8.55, 7.45 ],
            "rotation": { "origin": [ 8.0, 8.0, 8.0 ], "axis": "z", "angle": 45 },
            "faces": {
                "north": { "uv": [ 0, 0, 1, 16 ], "texture": "#m6", "rotation": 90 },
                "south": { "uv": [ 0, 0, 1, 16 ], "texture": "#m6", "rotation": 90 },
                "east":  { "uv": [ 0, 0, 1, 16 ], "texture": "#m6", "rotation": 90 },
                "west":  { "uv": [ 0, 0, 1, 16 ], "texture": "#m6", "rotation": 90 },
                "down":  { "uv": [ 0, 12, 1, 16 ], "texture": "#m6", "rotation": 90 },
                "up":    { "uv": [ 0, 0, 1, 4 ], "texture": "#m6", "rotation": 90 }
            }
        },
        {
            "comment": "minute hand",
            "from": [ 7.45, 0.29999999999999893, 6.35 ],
            "to": [ 8.55, 9.1, 7.45 ],
            "rotation": { "origin": [ 8.0, 8.0, 8.0 ], "axis": "z", "angle": -22.5 },
            "faces": {
                "north": { "uv": [ 0, 0, 1, 16 ], "texture": "#m7", "rotation": 180 },
                "south": { "uv": [ 0, 0, 1, 16 ], "texture": "#m7", "rotation": 180 },
                "east":  { "uv": [ 0, 0, 1, 16 ], "texture": "#m7", "rotation": 180 },
                "west":  { "uv": [ 0, 0, 1, 16 ], "texture": "#m7", "rotation": 180 },
                "down":  { "uv": [ 0, 12, 1, 16 ], "texture": "#m7", "rotation": 180 },
                "up":    { "uv": [ 0, 0, 1, 4 ], "texture": "#m7", "rotation": 180 }
            }
        },
        {
            "comment": "minute hand",
            "from": [ 7.45, 0.29999999999999893, 6.35 ],
            "to": [ 8.55, 9.1, 7.45 ],
            "faces": {
                "north": { "uv": [ 0, 0, 1, 16 ], "texture": "#m8", "rotation": 180 },
                "south": { "uv": [ 0, 0, 1, 16 ], "texture": "#m8", "rotation": 180 },
                "east":  { "uv": [ 0, 0, 1, 16 ], "texture": "#m8", "rotation": 180 },
                "west":  { "uv": [ 0, 0, 1, 16 ], "texture": "#m8", "rotation": 180 },
                "down":  { "uv": [ 0, 12, 1, 16 ], "texture": "#m8", "rotation": 180 },
                "up":    { "uv": [ 0, 0, 1, 4 ], "texture": "#m8", "rotation": 180 }
            }
        },
        {
            "comment": "minute hand",
            "from": [ 7.45, 0.29999999999999893, 6.35 ],
            "to": [ 8.55, 9.1, 7.45 ],
            "rotation": { "origin": [ 8.0, 8.0, 8.0 ], "axis": "z", "angle": 22.5 },
            "faces": {
                "north": { "uv": [ 0, 0, 1, 16 ], "texture": "#m9", "rotation": 180 },
                "south": { "uv": [ 0, 0, 1, 16 ], "texture": "#m9", "rotation": 180 },
                "east":  { "uv": [ 0, 0, 1, 16 ], "texture": "#m9", "rotation": 180 },
                "west":  { "uv": [ 0, 0, 1, 16 ], "texture": "#m9", "rotation": 180 },
                "down":  { "uv": [ 0, 12, 1, 16 ], "texture": "#m9", "rotation": 180 },
                "up":    { "uv": [ 0, 0, 1, 4 ], "texture": "#m9", "rotation": 180 }
            }
        },
        {
            "comment": "minute hand",
            "from": [ 7.45, 0.29999999999999893, 6.35 ],
            "to": [ 8.55, 9.1, 7.45 ],
            "rotation": { "origin": [ 8.0, 8.0, 8.0 ], "axis": "z", "angle": 45 },
            "faces": {
                "north": { "uv": [ 0, 0, 1, 16 ], "texture": "#m10", "rotation": 180 },
                "south": { "uv": [ 0, 0, 1, 16 ], "texture": "#m10", "rotation": 180 },
                "east":  { "uv": [ 0, 0, 1, 16 ], "texture": "#m10", "rotation": 180 },
                "west":  { "uv": [ 0, 0, 1, 16 ], "texture": "#m10", "rotation": 180 },
                "down":  { "uv": [ 0, 12, 1, 16 ], "texture": "#m10", "rotation": 180 },
                "up":    { "uv": [ 0, 0, 1, 4 ], "texture": "#m10", "rotation": 180 }
            }
        },
        {
            "comment": "minute hand",
            "from": [ 6.9, 7.45, 6.35 ],
            "to": [ 15.700000000000001, 8.55, 7.45 ],
            "rotation": { "origin": [ 8.0, 8.0, 8.0 ], "axis": "z", "angle": -22.5 },
            "faces": {
                "north": { "uv": [ 0, 0, 1, 16 ], "texture": "#m11", "rotation": 270 },
                "south": { "uv": [ 0, 0, 1, 16 ], "texture": "#m11", "rotation": 270 },
                "east":  { "uv": [ 0, 0, 1, 16 ], "texture": "#m11", "rotation": 270 },
                "west":  { "uv": [ 0, 0, 1, 16 ], "texture": "#m11", "rotation": 270 },
                "down":  { "uv": [ 0, 12, 1, 16 ], "texture": "#m11", "rotation": 270 },
                "up":    { "uv": [ 0, 0, 1, 4 ], "texture": "#m11", "rotation": 270 }
            }
        },
        {
            "comment": "minute hand",
            "from": [ 6.9, 7.45, 6.35 ],
            "to": [ 15.700000000000001, 8.55, 7.45 ],
            "faces": {
                "north": { "uv": [ 0, 0, 1, 16 ], "texture": "#m12", "rotation": 270 },
                "south": { "uv": [ 0, 0, 1, 16 ], "texture": "#m12", "rotation": 270 },
                "east":  { "uv": [ 0, 0, 1, 16 ], "texture": "#m12", "rotation": 270 },
                "west":  { "uv": [ 0, 0, 1, 16 ], "texture": "#m12", "rotation": 270 },
                "down":  { "uv": [ 0, 12, 1, 16 ], "texture": "#m12", "rotation": 270 },
                "up":    { "uv": [ 0, 0, 1, 4 ], "texture": "#m12", "rotation": 270 }
            }
        },
        {
            "comment": "minute hand",
            "from": [ 6.9, 7.45, 6.35 ],
            "to": [ 15.700000000000001, 8.55, 7.45 ],
            "rotation": { "origin": [ 8.0, 8.0, 8.0 ], "axis": "z", "angle": 22.5 },
            "faces": {
                "north": { "uv": [ 0, 0, 1, 16 ], "texture": "#m13", "rotation": 270 },
                "south": { "uv": [ 0, 0, 1, 16 ], "texture": "#m13", "rotation": 270 },
                "east":  { "uv": [ 0, 0, 1, 16 ], "texture": "#m13", "rotation": 270 },
                "west":  { "uv": [ 0, 0, 1, 16 ], "texture": "#m13", "rotation": 270 },
                "down":  { "uv": [ 0, 12, 1, 16 ], "texture": "#m13", "rotation": 270 },
                "up":    { "uv": [ 0, 0, 1, 4 ], "texture": "#m13", "rotation": 270 }
            }
        },
        {
            "comment": "minute hand",
            "from": [ 6.9, 7.45, 6.35 ],
            "to": [ 15.700000000000001, 8.55, 7.45 ],
            "rotation": { "origin": [ 8.0, 8.0, 8.0 ], "axis": "z", "angle": 45 },
            "faces": {
                "north": { "uv": [ 0, 0, 1, 16 ], "texture": "#m14", "rotation": 270 },
                "south": { "uv": [ 0, 0, 1, 16 ], "texture": "#m14", "rotation": 270 },
                "east":  { "uv": [ 0, 0, 1, 16 ], "texture": "#m14", "rotation": 270 },
                "west":  { "uv": [ 0, 0, 1, 16 ], "texture": "#m14", "rotation": 270 },
                "down":  { "uv": [ 0, 12, 1, 16 ], "texture": "#m14", "rotation": 270 },
                "up":    { "uv": [ 0, 0, 1, 4 ], "texture": "#m14", "rotation": 270 }
            }
        },
        {
            "comment": "hour hand",
            "from": [ 7.45, 6.9, 5.25 ],
            "to": [ 8.55, 13.5, 6.35 ],
            "rotation": { "origin": [ 8.0, 8.0, 8.0 ], "axis": "z", "angle": -22.5 },
            "faces": {
                "north": { "uv": [ 0, 4, 1, 16 ], "texture": "#h15" },
                "south": { "uv": [ 0, 4, 1, 16 ], "texture": "#h15" },
                "east":  { "uv": [ 0, 4, 1, 16 ], "texture": "#h15" },
                "west":  { "uv": [ 0, 4, 1, 16 ], "texture": "#h15" },
                "down":  { "uv": [ 0, 12, 1, 16 ], "texture": "#h15" },
                "up":    { "uv": [ 0, 0, 1, 4 ], "texture": "#h15" }
            }
        },
        {
            "comment": "hour hand",
            "from": [ 7.45, 6.9, 5.25 ],
            "to": [ 8.55, 13.5, 6.35 ],
            "faces": {
                "north": { "uv": [ 0, 4, 1, 16 ], "texture": "#h0" },
                "south": { "uv": [ 0, 4, 1, 16 ], "texture": "#h0" },
                "east":  { "uv": [ 0, 4, 1, 16 ], "texture": "#h0" },
                "west":  { "uv": [ 0, 4, 1, 16 ], "texture": "#h0" },
                "down":  { "uv": [ 0, 12, 1, 16 ], "texture": "#h0" },
                "up":    { "uv": [ 0, 0, 1, 4 ], "texture": "#h0" }
            }
        },
        {
            "comment": "hour hand",
            "from": [ 7.45, 6.9, 5.25 ],
            "to": [ 8.55, 13.5, 6.35 ],
            "rotation": { "origin": [ 8.0, 8.0, 8.0 ], "axis": "z", "angle": 22.5 },
            "faces": {
                "north": { "uv": [ 0, 4, 1, 16 ], "texture": "#h1" },
                "south": { "uv": [ 0, 4, 1, 16 ], "texture": "#h1" },
                "east":  { "uv": [ 0, 4, 1, 16 ], "texture": "#h1" },
                "west":  { "uv": [ 0, 4, 1, 16 ], "texture": "#h1" },
                "down":  { "uv": [ 0, 12, 1, 16 ], "texture": "#h1" },
                "up":    { "uv": [ 0, 0, 1, 4 ], "texture": "#h1" }
            }
        },
        {
            "comment": "hour hand",
            "from": [ 7.45, 6.9, 5.25 ],
            "to": [ 8.55, 13.5, 6.35 ],
            "rotation": { "origin": [ 8.0, 8.0, 8.0 ], "axis": "z", "angle": 45 },
            "faces": {
                "north": { "uv": [ 0, 4, 1, 16 ], "texture": "#h2" },
                "south": { "uv": [ 0, 4, 1, 16 ], "texture": "#h2" },
                "east":  { "uv": [ 0, 4, 1, 16 ], "texture": "#h2" },
                "west":  { "uv": [ 0, 4, 1, 16 ], "texture": "#h2" },
                "down":  { "uv": [ 0, 12, 1, 16 ], "texture": "#h2" },
                "up":    { "uv": [ 0, 0, 1, 4 ], "texture": "#h2" }
            }
        },
        {
            "comment": "hour hand",
            "from": [ 2.5, 7.45, 5.25 ],
            "to": [ 9.1, 8.55, 6.35 ],
            "rotation": { "origin": [ 8.0, 8.0, 8.0 ], "axis": "z", "angle": -22.5 },
            "faces": {
                "north": { "uv": [ 0, 4, 1, 16 ], "texture": "#h3", "rotation": 90 },
                "south": { "uv": [ 0, 4, 1, 16 ], "texture": "#h3", "rotation": 90 },
                "east":  { "uv": [ 0, 4, 1, 16 ], "texture": "#h3", "rotation": 90 },
                "west":  { "uv": [ 0, 4, 1, 16 ], "texture": "#h3", "rotation": 90 },
                "down":  { "uv": [ 0, 12, 1, 16 ], "texture": "#h3", "rotation": 90 },
                "up":    { "uv": [ 0, 0, 1, 4 ], "texture": "#h3", "rotation": 90 }
            }
        },
        {
            "comment": "hour hand",
            "from": [ 2.5, 7.45, 5.25 ],
            "to": [ 9.1, 8.55, 6.35 ],
            "faces": {
                "north": { "uv": [ 0, 4, 1, 16 ], "texture": "#h4", "rotation": 90 },
                "south": { "uv": [ 0, 4, 1, 16 ], "texture": "#h4", "rotation": 90 },
                "east":  { "uv": [ 0, 4, 1, 16 ], "texture": "#h4", "rotation": 90 },
                "west":  { "uv": [ 0, 4, 1, 16 ], "texture": "#h4", "rotation": 90 },
                "down":  { "uv": [ 0, 12, 1, 16 ], "texture": "#h4", "rotation": 90 },
                "up":    { "uv": [ 0, 0, 1, 4 ], "texture": "#h4", "rotation": 90 }
            }
        },
        {
            "comment": "hour hand",
            "from": [ 2.5, 7.45, 5.25 ],
            "to": [ 9.1, 8.55, 6.35 ],
            "rotation": { "origin": [ 8.0, 8.0, 8.0 ], "axis": "z", "angle": 22.5 },
            "faces": {
                "north": { "uv": [ 0, 4, 1, 16 ], "texture": "#h5", "rotation": 90 },
                "south": { "uv": [ 0, 4, 1, 16 ], "texture": "#h5", "rotation": 90 },
                "east":  { "uv": [ 0, 4, 1, 16 ], "texture": "#h5", "rotation": 90 },
                "west":  { "uv": [ 0, 4, 1, 16 ], "texture": "#h5", "rotation": 90 },
                "down":  { "uv": [ 0, 12, 1, 16 ], "texture": "#h5", "rotation": 90 },
                "up":    { "uv": [ 0, 0, 1, 4 ], "texture": "#h5", "rotation": 90 }
            }
        },
        {
            "comment": "hour hand",
            "from": [ 2.5, 7.45, 5.25 ],
            "to": [ 9.1, 8.55, 6.35 ],
            "rotation": { "origin": [ 8.0, 8.0, 8.0 ], "axis": "z", "angle": 45 },
            "faces": {
                "north": { "uv": [ 0, 4, 1, 16 ], "texture": "#h6", "rotation": 90 },
                "south": { "uv": [ 0, 4, 1, 16 ], "texture": "#h6", "rotation": 90 },
                "east":  { "uv": [ 0, 4, 1, 16 ], "texture": "#h6", "rotation": 90 },
                "west":  { "uv": [ 0, 4, 1, 16 ], "texture": "#h6", "rotation": 90 },
                "down":  { "uv": [ 0, 12, 1, 16 ], "texture": "#h6", "rotation": 90 },
                "up":    { "uv": [ 0, 0, 1, 4 ], "texture": "#h6", "rotation": 90 }
            }
        },
        {
            "comment": "hour hand",
            "from": [ 7.45, 2.5, 5.25 ],
            "to": [ 8.55, 9.1, 6.35 ],
            "rotation": { "origin": [ 8.0, 8.0, 8.0 ], "axis": "z", "angle": -22.5 },
            "faces": {
                "north": { "uv": [ 0, 4, 1, 16 ], "texture": "#h7", "rotation": 180 },
                "south": { "uv": [ 0, 4, 1, 16 ], "texture": "#h7", "rotation": 180 },
                "east":  { "uv": [ 0, 4, 1, 16 ], "texture": "#h7", "rotation": 180 },
                "west":  { "uv": [ 0, 4, 1, 16 ], "texture": "#h7", "rotation": 180 },
                "down":  { "uv": [ 0, 12, 1, 16 ], "texture": "#h7", "rotation": 180 },
                "up":    { "uv": [ 0, 0, 1, 4 ], "texture": "#h7", "rotation": 180 }
            }
        },
        {
            "comment": "hour hand",
            "from": [ 7.45, 2.5, 5.25 ],
            "to": [ 8.55, 9.1, 6.35 ],
            "faces": {
                "north": { "uv": [ 0, 4, 1, 16 ], "texture": "#h8", "rotation": 180 },
                "south": { "uv": [ 0, 4, 1, 16 ], "texture": "#h8", "rotation": 180 },
                "east":  { "uv": [ 0, 4, 1, 16 ], "texture": "#h8", "rotation": 180 },
                "west":  { "uv": [ 0, 4, 1, 16 ], "texture": "#h8", "rotation": 180 },
                "down":  { "uv": [ 0, 12, 1, 16 ], "texture": "#h8", "rotation": 180 },
                "up":    { "uv": [ 0, 0, 1, 4 ], "texture": "#h8", "rotation": 180 }
            }
        },
        {
            "comment": "hour hand",
            "from": [ 7.45, 2.5, 5.25 ],
            "to": [ 8.55, 9.1, 6.35 ],
            "rotation": { "origin": [ 8.0, 8.0, 8.0 ], "axis": "z", "angle": 22.5 },
            "faces": {
                "north": { "uv": [ 0, 4, 1, 16 ], "texture": "#h9", "rotation": 180 },
                "south": { "uv": [ 0, 4, 1, 16 ], "texture": "#h9", "rotation": 180 },
                "east":  { "uv": [ 0, 4, 1, 16 ], "texture": "#h9", "rotation": 180 },
                "west":  { "uv": [ 0, 4, 1, 16 ], "texture": "#h9", "rotation": 180 },
                "down":  { "uv": [ 0, 12, 1, 16 ], "texture": "#h9", "rotation": 180 },
                "up":    { "uv": [ 0, 0, 1, 4 ], "texture": "#h9", "rotation": 180 }
            }
        },
        {
            "comment": "hour hand",
            "from": [ 7.45, 2.5, 5.25 ],
            "to": [ 8.55, 9.1, 6.35 ],
            "rotation": { "origin": [ 8.0, 8.0, 8.0 ], "axis": "z", "angle": 45 },
            "faces": {
                "north": { "uv": [ 0, 4, 1, 16 ], "texture": "#h10", "rotation": 180 },
                "south": { "uv": [ 0, 4, 1, 16 ], "texture": "#h10", "rotation": 180 },
                "east":  { "uv": [ 0, 4, 1, 16 ], "texture": "#h10", "rotation": 180 },
                "west":  { "uv": [ 0, 4, 1, 16 ], "texture": "#h10", "rotation": 180 },
                "down":  { "uv": [ 0, 12, 1, 16 ], "texture": "#h10", "rotation": 180 },
                "up":    { "uv": [ 0, 0, 1, 4 ], "texture": "#h10", "rotation": 180 }
            }
        },
        {
            "comment": "hour hand",
            "from": [ 6.9, 7.45, 5.25 ],
            "to": [ 13.5, 8.55, 6.35 ],
            "rotation": { "origin": [ 8.0, 8.0, 8.0 ], "axis": "z", "angle": -22.5 },
            "faces": {
                "north": { "uv": [ 0, 4, 1, 16 ], "texture": "#h11", "rotation": 270 },
                "south": { "uv": [ 0, 4, 1, 16 ], "texture": "#h11", "rotation": 270 },
                "east":  { "uv": [ 0, 4, 1, 16 ], "texture": "#h11", "rotation": 270 },
                "west":  { "uv": [ 0, 4, 1, 16 ], "texture": "#h11", "rotation": 270 },
                "down":  { "uv": [ 0, 12, 1, 16 ], "texture": "#h11", "rotation": 270 },
                "up":    { "uv": [ 0, 0, 1, 4 ], "texture": "#h11", "rotation": 270 }
            }
        },
        {
            "comment": "hour hand",
            "from": [ 6.9, 7.45, 5.25 ],
            "to": [ 13.5, 8.55, 6.35 ],
            "faces": {
                "north": { "uv": [ 0, 4, 1, 16 ], "texture": "#h12", "rotation": 270 },
                "south": { "uv": [ 0, 4, 1, 16 ], "texture": "#h12", "rotation": 270 },
                "east":  { "uv": [ 0, 4, 1, 16 ], "texture": "#h12", "rotation": 270 },
                "west":  { "uv": [ 0, 4, 1, 16 ], "texture": "#h12", "rotation": 270 },
                "down":  { "uv": [ 0, 12, 1, 16 ], "texture": "#h12", "rotation": 270 },
                "up":    { "uv": [ 0, 0, 1, 4 ], "texture": "#h12", "rotation": 270 }
            }
        },
        {
            "comment": "hour hand",
            "from": [ 6.9, 7.45, 5.25 ],
            "to": [ 13.5, 8.55, 6.35 ],
            "rotation": { "origin": [ 8.0, 8.0, 8.0 ], "axis": "z", "angle": 22.5 },
            "faces": {
                "north": { "uv": [ 0, 4, 1, 16 ], "texture": "#h13", "rotation": 270 },
                "south": { "uv": [ 0, 4, 1, 16 ], "texture": "#h13", "rotation": 270 },
                "east":  { "uv": [ 0, 4, 1, 16 ], "texture": "#h13", "rotation": 270 },
                "west":  { "uv": [ 0, 4, 1, 16 ], "texture": "#h13", "rotation": 270 },
                "down":  { "uv": [ 0, 12, 1, 16 ], "texture": "#h13", "rotation": 270 },
                "up":    { "uv": [ 0, 0, 1, 4 ], "texture": "#h13", "rotation": 270 }
            }
        },
        {
            "comment": "hour hand",
            "from": [ 6.9, 7.45, 5.25 ],
            "to": [ 13.5, 8.55, 6.35 ],
            "rotation": { "origin": [ 8.0, 8.0, 8.0 ], "axis": "z", "angle": 45 },
            "faces": {
                "north": { "uv": [ 0, 4, 1, 16 ], "texture": "#h14", "rotation": 270 },
                "south": { "uv": [ 0, 4, 1, 16 ], "texture": "#h14", "rotation": 270 },
                "east":  { "uv": [ 0, 4, 1, 16 ], "texture": "#h14", "rotation": 270 },
                "west":  { "uv": [ 0, 4, 1, 16 ], "texture": "#h14", "rotation": 270 },
                "down":  { "uv": [ 0, 12, 1, 16 ], "texture": "#h14", "rotation": 270 },
                "up":    { "uv": [ 0, 0, 1, 4 ], "texture": "#h14", "rotation": 270 }
            }
        }
    ]
}
